dside/DSI.py
dside/__init__.py
dside-2.3.2.dist-info/LICENSE
dside-2.3.2.dist-info/METADATA
dside-2.3.2.dist-info/WHEEL
dside-2.3.2.dist-info/top_level.txt
dside-2.3.2.dist-info/RECORD
