Metadata-Version: 2.1
Name: dside
Version: 2.3.2
Summary: Design space identification tool for plotting and analysing design spaces (2D and 3D).
Home-page: https://github.com/stvsach/dside
Author: Steven Sachio
Author-email: stevensachio1506@gmail.com
License: MIT
Classifier: Development Status :: 2 - Pre-Alpha
Classifier: Programming Language :: Python :: 3
Classifier: License :: OSI Approved :: MIT License
Classifier: Operating System :: OS Independent
Classifier: Intended Audience :: Education
Requires-Python: >=3.9
License-File: LICENSE
Requires-Dist: numpy
Requires-Dist: matplotlib
Requires-Dist: pandas
Requires-Dist: scipy
